[
  {
    "Id": "interu1",
    "Title": "スポーツサスペンション1",
    "Description": "衝撃​吸収​を​付加​し、​安定​性​を​増し​ます。​乗り物​が​簡単​に​ひっくり返っ​て​しまう​の​を​防ぐ​の​に​適し​て​い​ます。​この​サスペンション​は​小型​です​が、​弾力​は​しっかり​し​て​い​ます。"
  },
  {
    "Id": "interu2",
    "Title": "スポーツサスペンション2",
    "Description": "衝撃​吸収​を​付加​し、​安定​性​を​増し​ます。​乗り物​が​簡単​に​ひっくり返っ​て​しまう​の​を​防ぐ​の​に​適し​て​い​ます。​この​サスペンション​は​小型​です​が、​弾力​は​しっかり​し​て​い​ます。"
  },
  {
    "Id": "interu3",
    "Title": "スポーツサスペンション3",
    "Description": "衝撃​吸収​を​付加​し、​安定​性​を​増し​ます。​乗り物​が​簡単​に​ひっくり返っ​て​しまう​の​を​防ぐ​の​に​適し​て​い​ます。​この​サスペンション​は​小型​です​が、​弾力​は​しっかり​し​て​い​ます。"
  },
  {
    "Id": "interu4",
    "Title": "スポーツサスペンション4",
    "Description": "衝撃​吸収​を​付加​し、​安定​性​を​増し​ます。​乗り物​が​簡単​に​ひっくり返っ​て​しまう​の​を​防ぐ​の​に​適し​て​い​ます。​この​サスペンション​は​小型​です​が、​弾力​は​しっかり​し​て​い​ます。"
  },
  {
    "Id": "interu5",
    "Title": "スポーツサスペンション5",
    "Description": "衝撃​吸収​を​付加​し、​安定​性​を​増し​ます。​乗り物​が​簡単​に​ひっくり返っ​て​しまう​の​を​防ぐ​の​に​適し​て​い​ます。​この​サスペンション​は​小型​です​が、​弾力​は​しっかり​し​て​い​ます。"
  },
  {
    "Id": "interu6",
    "Title": "オフロードサスペンション1",
    "Description": "衝撃​吸収​を​付加​し、​安定​性​を​増し​ます。​乗り物​が​簡単​に​ひっくり返っ​て​しまう​の​を​防ぐ​の​に​適し​て​い​ます。​この​サスペンション​は​弾力​性​が​高く、​オフロード​用​の​乗り物​に​最適​です。"
  },
  {
    "Id": "interu7",
    "Title": "オフロードサスペンション2",
    "Description": "衝撃​吸収​を​付加​し、​安定​性​を​増し​ます。​乗り物​が​簡単​に​ひっくり返っ​て​しまう​の​を​防ぐ​の​に​適し​て​い​ます。​この​サスペンション​は​弾力​性​が​高く、​オフロード​用​の​乗り物​に​最適​です。"
  },
  {
    "Id": "interu8",
    "Title": "オフロードサスペンション3",
    "Description": "衝撃​吸収​を​付加​し、​安定​性​を​増し​ます。​乗り物​が​簡単​に​ひっくり返っ​て​しまう​の​を​防ぐ​の​に​適し​て​い​ます。​この​サスペンション​は​弾力​性​が​高く、​オフロード​用​の​乗り物​に​最適​です。"
  },
  {
    "Id": "interu9",
    "Title": "オフロードサスペンション4",
    "Description": "衝撃​吸収​を​付加​し、​安定​性​を​増し​ます。​乗り物​が​簡単​に​ひっくり返っ​て​しまう​の​を​防ぐ​の​に​適し​て​い​ます。​この​サスペンション​は​弾力​性​が​高く、​オフロード​用​の​乗り物​に​最適​です。"
  },
  {
    "Id": "interu10",
    "Title": "オフロードサスペンション5",
    "Description": "衝撃​吸収​を​付加​し、​安定​性​を​増し​ます。​乗り物​が​簡単​に​ひっくり返っ​て​しまう​の​を​防ぐ​の​に​適し​て​い​ます。​この​サスペンション​は​弾力​性​が​高く、​オフロード​用​の​乗り物​に​最適​です。"
  },
  {
    "Id": "interu11",
    "Title": "運転席1",
    "Description": "ベアリング​を​左右​に​回し​ます。​エンジン​に​接続​する​と、​動く​方向​を​コントロール​する​こと​が​でき​ます。​また、​トリガー​に​接続​する​と、​運転​席​から​動作​さ​せる​こと​が​でき​ます。​レベル​5​の​運転​席​で​は、​（​E​）​を​押す​こと​で、​接続​具​で​接続​し​た​ベアリング​の​ステアリング​設定​が​アン​ロック​さ​れ​ます。"
  },
  {
    "Id": "interu12",
    "Title": "運転席2",
    "Description": "ベアリング​を​左右​に​回し​ます。​エンジン​に​接続​する​と、​動く​方向​を​コントロール​する​こと​が​でき​ます。​また、​トリガー​に​接続​する​と、​運転​席​から​動作​さ​せる​こと​が​でき​ます。​レベル​5​の​運転​席​で​は、​（​E​）​を​押す​こと​で、​接続​具​で​接続​し​た​ベアリング​の​ステアリング​設定​が​アン​ロック​さ​れ​ます。"
  },
  {
    "Id": "interu13",
    "Title": "運転席3",
    "Description": "ベアリング​を​左右​に​回し​ます。​エンジン​に​接続​する​と、​動く​方向​を​コントロール​する​こと​が​でき​ます。​また、​トリガー​に​接続​する​と、​運転​席​から​動作​さ​せる​こと​が​でき​ます。​レベル​5​の​運転​席​で​は、​（​E​）​を​押す​こと​で、​接続​具​で​接続​し​た​ベアリング​の​ステアリング​設定​が​アン​ロック​さ​れ​ます。"
  },
  {
    "Id": "interu14",
    "Title": "運転席4",
    "Description": "ベアリング​を​左右​に​回し​ます。​エンジン​に​接続​する​と、​動く​方向​を​コントロール​する​こと​が​でき​ます。​また、​トリガー​に​接続​する​と、​運転​席​から​動作​さ​せる​こと​が​でき​ます。​レベル​5​の​運転​席​で​は、​（​E​）​を​押す​こと​で、​接続​具​で​接続​し​た​ベアリング​の​ステアリング​設定​が​アン​ロック​さ​れ​ます。"
  },
  {
    "Id": "interu15",
    "Title": "運転席5",
    "Description": "ベアリング​を​左右​に​回し​ます。​エンジン​に​接続​する​と、​動く​方向​を​コントロール​する​こと​が​でき​ます。​また、​トリガー​に​接続​する​と、​運転​席​から​動作​さ​せる​こと​が​でき​ます。​レベル​5​の​運転​席​で​は、​（​E​）​を​押す​こと​で、​接続​具​で​接続​し​た​ベアリング​の​ステアリング​設定​が​アン​ロック​さ​れ​ます。"
  },
  {
    "Id": "interu16",
    "Title": "運転サドル1",
    "Description": "ベアリング​を​左右​に​回し​ます。​エンジン​に​接続​する​と、​動く​方向​を​コントロール​する​こと​が​でき​ます。​また、​トリガー​に​接続​する​と、​サドル​から​動作​さ​せる​こと​が​でき​ます。​レベル​5​の​運転​サドル​で​は、​（​E​）​を​押す​こと​で、​接続​具​で​接続​し​た​ベアリング​の​ステアリング​設定​が​アン​ロック​さ​れ​ます。"
  },
  {
    "Id": "interu17",
    "Title": "運転サドル2",
    "Description": "ベアリング​を​左右​に​回し​ます。​エンジン​に​接続​する​と、​動く​方向​を​コントロール​する​こと​が​でき​ます。​また、​トリガー​に​接続​する​と、​サドル​から​動作​さ​せる​こと​が​でき​ます。​レベル​5​の​運転​サドル​で​は、​（​E​）​を​押す​こと​で、​接続​具​で​接続​し​た​ベアリング​の​ステアリング​設定​が​アン​ロック​さ​れ​ます。"
  },
  {
    "Id": "interu18",
    "Title": "運転サドル3",
    "Description": "ベアリング​を​左右​に​回し​ます。​エンジン​に​接続​する​と、​動く​方向​を​コントロール​する​こと​が​でき​ます。​また、​トリガー​に​接続​する​と、​サドル​から​動作​さ​せる​こと​が​でき​ます。​レベル​5​の​運転​サドル​で​は、​（​E​）​を​押す​こと​で、​接続​具​で​接続​し​た​ベアリング​の​ステアリング​設定​が​アン​ロック​さ​れ​ます。"
  },
  {
    "Id": "interu19",
    "Title": "運転サドル4",
    "Description": "ベアリング​を​左右​に​回し​ます。​エンジン​に​接続​する​と、​動く​方向​を​コントロール​する​こと​が​でき​ます。​また、​トリガー​に​接続​する​と、​サドル​から​動作​さ​せる​こと​が​でき​ます。​レベル​5​の​運転​サドル​で​は、​（​E​）​を​押す​こと​で、​接続​具​で​接続​し​た​ベアリング​の​ステアリング​設定​が​アン​ロック​さ​れ​ます。"
  },
  {
    "Id": "interu20",
    "Title": "運転サドル5",
    "Description": "ベアリング​を​左右​に​回し​ます。​エンジン​に​接続​する​と、​動く​方向​を​コントロール​する​こと​が​でき​ます。​また、​トリガー​に​接続​する​と、​サドル​から​動作​さ​せる​こと​が​でき​ます。​レベル​5​の​運転​サドル​で​は、​（​E​）​を​押す​こと​で、​接続​具​で​接続​し​た​ベアリング​の​ステアリング​設定​が​アン​ロック​さ​れ​ます。"
  },
  {
    "Id": "interu21",
    "Title": "座席1",
    "Description": "立ち​続ける​の​を​避ける​の​に​使い​ます。​座っ​て​リラックス​し​たり、​乗り物​に​取り付け​て​フレンド​が​一緒​について​こ​られる​よう​に​し​ましょ​う。​トリガー​に​接続​し​て、​他​の​インタラクティブ​パーツ​を​座席​から​動作​さ​せ​られる​よう​に​する​こと​が​でき​ます。"
  },
  {
    "Id": "interu22",
    "Title": "座席2",
    "Description": "立ち​続ける​の​を​避ける​の​に​使い​ます。​座っ​て​リラックス​し​たり、​乗り物​に​取り付け​て​フレンド​が​一緒​について​こ​られる​よう​に​し​ましょ​う。​トリガー​に​接続​し​て、​他​の​インタラクティブ​パーツ​を​座席​から​動作​さ​せ​られる​よう​に​する​こと​が​でき​ます。"
  },
  {
    "Id": "interu23",
    "Title": "座席3",
    "Description": "立ち​続ける​の​を​避ける​の​に​使い​ます。​座っ​て​リラックス​し​たり、​乗り物​に​取り付け​て​フレンド​が​一緒​について​こ​られる​よう​に​し​ましょ​う。​トリガー​に​接続​し​て、​他​の​インタラクティブ​パーツ​を​座席​から​動作​さ​せ​られる​よう​に​する​こと​が​でき​ます。"
  },
  {
    "Id": "interu24",
    "Title": "座席4",
    "Description": "立ち​続ける​の​を​避ける​の​に​使い​ます。​座っ​て​リラックス​し​たり、​乗り物​に​取り付け​て​フレンド​が​一緒​について​こ​られる​よう​に​し​ましょ​う。​トリガー​に​接続​し​て、​他​の​インタラクティブ​パーツ​を​座席​から​動作​さ​せ​られる​よう​に​する​こと​が​でき​ます。"
  },
  {
    "Id": "interu25",
    "Title": "座席5",
    "Description": "立ち​続ける​の​を​避ける​の​に​使い​ます。​座っ​て​リラックス​し​たり、​乗り物​に​取り付け​て​フレンド​が​一緒​について​こ​られる​よう​に​し​ましょ​う。​トリガー​に​接続​し​て、​他​の​インタラクティブ​パーツ​を​座席​から​動作​さ​せ​られる​よう​に​する​こと​が​でき​ます。"
  },
  {
    "Id": "interu26",
    "Title": "サドル1",
    "Description": "立ち​続ける​の​を​避ける​の​に​使い​ます。​座っ​て​リラックス​し​たり、​乗り物​に​取り付け​て​フレンド​が​一緒​について​こ​られる​よう​に​し​ましょ​う。​トリガー​に​接続​し​て、​他​の​インタラクティブ​パーツ​を​サドル​から​動作​さ​せ​られる​よう​に​する​こと​が​でき​ます。"
  },
  {
    "Id": "interu27",
    "Title": "サドル2",
    "Description": "立ち​続ける​の​を​避ける​の​に​使い​ます。​座っ​て​リラックス​し​たり、​乗り物​に​取り付け​て​フレンド​が​一緒​について​こ​られる​よう​に​し​ましょ​う。​トリガー​に​接続​し​て、​他​の​インタラクティブ​パーツ​を​サドル​から​動作​さ​せ​られる​よう​に​する​こと​が​でき​ます。"
  },
  {
    "Id": "interu28",
    "Title": "サドル3",
    "Description": "立ち​続ける​の​を​避ける​の​に​使い​ます。​座っ​て​リラックス​し​たり、​乗り物​に​取り付け​て​フレンド​が​一緒​について​こ​られる​よう​に​し​ましょ​う。​トリガー​に​接続​し​て、​他​の​インタラクティブ​パーツ​を​サドル​から​動作​さ​せ​られる​よう​に​する​こと​が​でき​ます。"
  },
  {
    "Id": "interu29",
    "Title": "サドル4",
    "Description": "立ち​続ける​の​を​避ける​の​に​使い​ます。​座っ​て​リラックス​し​たり、​乗り物​に​取り付け​て​フレンド​が​一緒​について​こ​られる​よう​に​し​ましょ​う。​トリガー​に​接続​し​て、​他​の​インタラクティブ​パーツ​を​サドル​から​動作​さ​せ​られる​よう​に​する​こと​が​でき​ます。"
  },
  {
    "Id": "interu30",
    "Title": "サドル5",
    "Description": "立ち​続ける​の​を​避ける​の​に​使い​ます。​座っ​て​リラックス​し​たり、​乗り物​に​取り付け​て​フレンド​が​一緒​について​こ​られる​よう​に​し​ましょ​う。​トリガー​に​接続​し​て、​他​の​インタラクティブ​パーツ​を​サドル​から​動作​さ​せ​られる​よう​に​する​こと​が​でき​ます。"
  },
  {
    "Id": "interu31",
    "Title": "ガスエンジン1",
    "Description": "一定​の​速度​と​調整​可能​な​パワー​を​備え​た​エンジン。​乗り物​の​動力​に​最適​です。​運転​席​や​トリガー​に​接続​する​こと​が​でき​ます。​アップ​グレード​する​と​接続​点​が​増え、​ガス​消費​が​減り​ます。"
  },
  {
    "Id": "interu32",
    "Title": "ガスエンジン2",
    "Description": "一定​の​速度​と​調整​可能​な​パワー​を​備え​た​エンジン。​乗り物​の​動力​に​最適​です。​運転​席​や​トリガー​に​接続​する​こと​が​でき​ます。​アップ​グレード​する​と​接続​点​が​増え、​ガス​消費​が​減り​ます。"
  },
  {
    "Id": "interu33",
    "Title": "ガスエンジン3",
    "Description": "一定​の​速度​と​調整​可能​な​パワー​を​備え​た​エンジン。​乗り物​の​動力​に​最適​です。​運転​席​や​トリガー​に​接続​する​こと​が​でき​ます。​アップ​グレード​する​と​接続​点​が​増え、​ガス​消費​が​減り​ます。"
  },
  {
    "Id": "interu34",
    "Title": "ガスエンジン4",
    "Description": "一定​の​速度​と​調整​可能​な​パワー​を​備え​た​エンジン。​乗り物​の​動力​に​最適​です。​運転​席​や​トリガー​に​接続​する​こと​が​でき​ます。​アップ​グレード​する​と​接続​点​が​増え、​ガス​消費​が​減り​ます。"
  },
  {
    "Id": "interu35",
    "Title": "ガスエンジン5",
    "Description": "一定​の​速度​と​調整​可能​な​パワー​を​備え​た​エンジン。​乗り物​の​動力​に​最適​です。​運転​席​や​トリガー​に​接続​する​こと​が​でき​ます。​アップ​グレード​する​と​接続​点​が​増え、​ガス​消費​が​減り​ます。"
  },
  {
    "Id": "interu36",
    "Title": "電気エンジン1",
    "Description": "ベアリング​の​動力​に​なり​ます。​一定​の​パワー​と、​調整​可能​な​速度​を​備え​て​い​ます。​速度​調整​可能​な​力​の​弱い​エンジン​です。​運転​席​や​トリガー​に​接続​する​こと​が​でき​ます。​アップ​グレード​する​と​接続​点​が​増え、​バッテリー​消費​が​減り​ます。"
  },
  {
    "Id": "interu37",
    "Title": "電気エンジン2",
    "Description": "ベアリング​の​動力​に​なり​ます。​一定​の​パワー​と、​調整​可能​な​速度​を​備え​て​い​ます。​速度​調整​可能​な​力​の​弱い​エンジン​です。​運転​席​や​トリガー​に​接続​する​こと​が​でき​ます。​アップ​グレード​する​と​接続​点​が​増え、​バッテリー​消費​が​減り​ます。"
  },
  {
    "Id": "interu38",
    "Title": "電気エンジン3",
    "Description": "ベアリング​の​動力​に​なり​ます。​一定​の​パワー​と、​調整​可能​な​速度​を​備え​て​い​ます。​速度​調整​可能​な​力​の​弱い​エンジン​です。​運転​席​や​トリガー​に​接続​する​こと​が​でき​ます。​アップ​グレード​する​と​接続​点​が​増え、​バッテリー​消費​が​減り​ます。"
  },
  {
    "Id": "interu39",
    "Title": "電気エンジン4",
    "Description": "ベアリング​の​動力​に​なり​ます。​一定​の​パワー​と、​調整​可能​な​速度​を​備え​て​い​ます。​速度​調整​可能​な​力​の​弱い​エンジン​です。​運転​席​や​トリガー​に​接続​する​こと​が​でき​ます。​アップ​グレード​する​と​接続​点​が​増え、​バッテリー​消費​が​減り​ます。"
  },
  {
    "Id": "interu40",
    "Title": "電気エンジン5",
    "Description": "ベアリング​の​動力​に​なり​ます。​一定​の​パワー​と、​調整​可能​な​速度​を​備え​て​い​ます。​速度​調整​可能​な​力​の​弱い​エンジン​です。​運転​席​や​トリガー​に​接続​する​こと​が​でき​ます。​アップ​グレード​する​と​接続​点​が​増え、​バッテリー​消費​が​減り​ます。"
  },
  {
    "Id": "interu41",
    "Title": "スラスター1",
    "Description": "これら​が​十分​に​あれ​ば​物​を​飛ばす​こと​が​でき​ます。​動作​さ​せる​に​は、​トリガー​や​運転​席​に​接続​する​必要​が​あり​ます。​アップ​グレード​する​と、​ガス​消費​が​減り​ます。"
  },
  {
    "Id": "interu42",
    "Title": "スラスター2",
    "Description": "これら​が​十分​に​あれ​ば​物​を​飛ばす​こと​が​でき​ます。​動作​さ​せる​に​は、​トリガー​や​運転​席​に​接続​する​必要​が​あり​ます。​アップ​グレード​する​と、​ガス​消費​が​減り​ます。"
  },
  {
    "Id": "interu43",
    "Title": "スラスター3",
    "Description": "これら​が​十分​に​あれ​ば​物​を​飛ばす​こと​が​でき​ます。​動作​さ​せる​に​は、​トリガー​や​運転​席​に​接続​する​必要​が​あり​ます。​アップ​グレード​する​と、​ガス​消費​が​減り​ます。"
  },
  {
    "Id": "interu44",
    "Title": "スラスター4",
    "Description": "これら​が​十分​に​あれ​ば​物​を​飛ばす​こと​が​でき​ます。​動作​さ​せる​に​は、​トリガー​や​運転​席​に​接続​する​必要​が​あり​ます。​アップ​グレード​する​と、​ガス​消費​が​減り​ます。"
  },
  {
    "Id": "interu45",
    "Title": "スラスター5",
    "Description": "これら​が​十分​に​あれ​ば​物​を​飛ばす​こと​が​でき​ます。​動作​さ​せる​に​は、​トリガー​や​運転​席​に​接続​する​必要​が​あり​ます。​アップ​グレード​する​と、​ガス​消費​が​減り​ます。"
  },
  {
    "Id": "interu46",
    "Title": "コントローラー1",
    "Description": "ベアリング​が​順序​どおり​に​回転​する​よう​に​でき​ます。​変形​する​作成​物​を​建造​する​のに​最適​です。​ベアリング​に​接続​する​必要​が​あり​ます。​トリガー​や​運転​席​を​コントローラー​に​接続​する​こと​で​動作​し​ます。"
  },
  {
    "Id": "interu47",
    "Title": "コントローラー2",
    "Description": "ベアリング​が​順序​どおり​に​回転​する​よう​に​でき​ます。​変形​する​作成​物​を​建造​する​のに​最適​です。​ベアリング​に​接続​する​必要​が​あり​ます。​トリガー​や​運転​席​を​コントローラー​に​接続​する​こと​で​動作​し​ます。"
  },
  {
    "Id": "interu48",
    "Title": "コントローラー3",
    "Description": "ベアリング​が​順序​どおり​に​回転​する​よう​に​でき​ます。​変形​する​作成​物​を​建造​する​のに​最適​です。​ベアリング​に​接続​する​必要​が​あり​ます。​トリガー​や​運転​席​を​コントローラー​に​接続​する​こと​で​動作​し​ます。"
  },
  {
    "Id": "interu49",
    "Title": "コントローラー4",
    "Description": "ベアリング​が​順序​どおり​に​回転​する​よう​に​でき​ます。​変形​する​作成​物​を​建造​する​のに​最適​です。​ベアリング​に​接続​する​必要​が​あり​ます。​トリガー​や​運転​席​を​コントローラー​に​接続​する​こと​で​動作​し​ます。"
  },
  {
    "Id": "interu50",
    "Title": "コントローラー5",
    "Description": "ベアリング​が​順序​どおり​に​回転​する​よう​に​でき​ます。​変形​する​作成​物​を​建造​する​のに​最適​です。​ベアリング​に​接続​する​必要​が​あり​ます。​トリガー​や​運転​席​を​コントローラー​に​接続​する​こと​で​動作​し​ます。"
  },
  {
    "Id": "interu51",
    "Title": "センサー1",
    "Description": "検知​し​たり、​動作​さ​せ​たり​し​ます！​センサー​は​物体​の​表面​を​検知​する​と​動作​し​ます。​範囲​は​ブロック​10​個​分​です。​エンジン、​スラスター、​コントローラー​など​を​動作​さ​せる​こと​が​でき​ます。"
  },
  {
    "Id": "interu52",
    "Title": "センサー2",
    "Description": "検知​し​たり、​動作​さ​せ​たり​し​ます！​センサー​は​物体​の​表面​を​検知​する​と​動作​し​ます。​範囲​は​ブロック​10​個​分​です。​エンジン、​スラスター、​コントローラー​など​を​動作​さ​せる​こと​が​でき​ます。"
  },
  {
    "Id": "interu53",
    "Title": "センサー3",
    "Description": "検知​し​たり、​動作​さ​せ​たり​し​ます！​センサー​は​物体​の​表面​を​検知​する​と​動作​し​ます。​範囲​は​ブロック​10​個​分​です。​エンジン、​スラスター、​コントローラー​など​を​動作​さ​せる​こと​が​でき​ます。"
  },
  {
    "Id": "interu54",
    "Title": "センサー4",
    "Description": "検知​し​たり、​動作​さ​せ​たり​し​ます！​センサー​は​物体​の​表面​を​検知​する​と​動作​し​ます。​範囲​は​ブロック​10​個​分​です。​エンジン、​スラスター、​コントローラー​など​を​動作​さ​せる​こと​が​でき​ます。"
  },
  {
    "Id": "interu55",
    "Title": "センサー5",
    "Description": "検知​し​たり、​動作​さ​せ​たり​し​ます！​センサー​は​物体​の​表面​を​検知​する​と​動作​し​ます。​範囲​は​ブロック​10​個​分​です。​エンジン、​スラスター、​コントローラー​など​を​動作​さ​せる​こと​が​でき​ます。"
  },
  {
    "Id": "interu56",
    "Title": "ピストン1",
    "Description": "伸び​て、​縮み​ます！​トリガー​に​接続​し​て​動作​さ​せ​ます。​ピストン​は、​コントローラー​に​接続​し​て、​順序​どおり​に​伸び​縮み​さ​せる​こと​も​でき​ます。​印象​的​な​作成​物​を​作る​のに​最適​です。"
  },
  {
    "Id": "interu57",
    "Title": "ピストン2",
    "Description": "伸び​て、​縮み​ます！​トリガー​に​接続​し​て​動作​さ​せ​ます。​ピストン​は、​コントローラー​に​接続​し​て、​順序​どおり​に​伸び​縮み​さ​せる​こと​も​でき​ます。​印象​的​な​作成​物​を​作る​のに​最適​です。"
  },
  {
    "Id": "interu58",
    "Title": "ピストン3",
    "Description": "伸び​て、​縮み​ます！​トリガー​に​接続​し​て​動作​さ​せ​ます。​ピストン​は、​コントローラー​に​接続​し​て、​順序​どおり​に​伸び​縮み​さ​せる​こと​も​でき​ます。​印象​的​な​作成​物​を​作る​のに​最適​です。"
  },
  {
    "Id": "interu59",
    "Title": "ピストン4",
    "Description": "伸び​て、​縮み​ます！​トリガー​に​接続​し​て​動作​さ​せ​ます。​ピストン​は、​コントローラー​に​接続​し​て、​順序​どおり​に​伸び​縮み​さ​せる​こと​も​でき​ます。​印象​的​な​作成​物​を​作る​のに​最適​です。"
  },
  {
    "Id": "interu60",
    "Title": "ピストン5",
    "Description": "伸び​て、​縮み​ます！​トリガー​に​接続​し​て​動作​さ​せ​ます。​ピストン​は、​コントローラー​に​接続​し​て、​順序​どおり​に​伸び​縮み​さ​せる​こと​も​でき​ます。​印象​的​な​作成​物​を​作る​のに​最適​です。"
  }
]