[
  {
    "Id": "blk1",
    "Title": "Scrap Wood Block"
  },
  {
    "Id": "blk2",
    "Title": "Wood Block 2"
  },
  {
    "Id": "blk3",
    "Title": "Wood Block 3"
  },
  {
    "Id": "blk4",
    "Title": "Scrap Metal Block"
  },
  {
    "Id": "blk5",
    "Title": "Metal Block 2"
  },
  {
    "Id": "blk6",
    "Title": "Metal Block 3"
  },
  {
    "Id": "blk7",
    "Title": "Scrap Stone Block"
  },
  {
    "Id": "blk8",
    "Title": "Concrete Block 2"
  },
  {
    "Id": "blk9",
    "Title": "Concrete Block 3"
  },
  {
    "Id": "blk10",
    "Title": "Cracked Concrete Block"
  },
  {
    "Id": "blk11",
    "Title": "Concrete Slab Block"
  },
  {
    "Id": "blk12",
    "Title": "Rusted Metal Block"
  },
  {
    "Id": "blk13",
    "Title": "Extruded Metal Block"
  },
  {
    "Id": "blk14",
    "Title": "Bubble Plastic Block"
  },
  {
    "Id": "blk15",
    "Title": "Plastic Block"
  },
  {
    "Id": "blk16",
    "Title": "Insulation Block"
  },
  {
    "Id": "blk17",
    "Title": "Plaster Block"
  },
  {
    "Id": "blk18",
    "Title": "Carpet Block"
  },
  {
    "Id": "blk19",
    "Title": "Painted Wall Block"
  },
  {
    "Id": "blk20",
    "Title": "Net Block"
  },
  {
    "Id": "blk21",
    "Title": "Solid Net Block"
  },
  {
    "Id": "blk22",
    "Title": "Punched Steel Block"
  },
  {
    "Id": "blk23",
    "Title": "Striped Net Block"
  },
  {
    "Id": "blk24",
    "Title": "Square Mesh Block"
  },
  {
    "Id": "blk25",
    "Title": "Restroom Block"
  },
  {
    "Id": "blk26",
    "Title": "Diamond Plate Block"
  },
  {
    "Id": "blk27",
    "Title": "Aluminum Block"
  },
  {
    "Id": "blk28",
    "Title": "Worn Metal Block"
  },
  {
    "Id": "blk29",
    "Title": "Spaceship Floor Block"
  },
  {
    "Id": "blk30",
    "Title": "Sand Block"
  },
  {
    "Id": "blk31",
    "Title": "Armored Glass Block"
  },
  {
    "Id": "blk32",
    "Title": "Бетонный блок"
  },
  {
    "Id": "blk33",
    "Title": "Деревянный блок"
  },
  {
    "Id": "blk34",
    "Title": "Металлический блок"
  },
  {
    "Id": "blk35",
    "Title": "Блок-барьер"
  },
  {
    "Id": "blk36",
    "Title": "Блок-плитка"
  },
  {
    "Id": "blk37",
    "Title": "Кирпичный блок"
  },
  {
    "Id": "blk38",
    "Title": "Стеклянный блок"
  },
  {
    "Id": "blk39",
    "Title": "Стеклянный блок-плитка"
  },
  {
    "Id": "blk40",
    "Title": "Путь - легкий блок"
  },
  {
    "Id": "blk41",
    "Title": "Ремонтный корабль: блок"
  },
  {
    "Id": "blk42",
    "Title": "Картонный блок"
  }
]