[
  {
    "Id": "other1",
    "Title": "Connect Tool"
  },
  {
    "Id": "other2",
    "Title": "Paint Tool"
  },
  {
    "Id": "other3",
    "Title": "Weld Tool"
  },
  {
    "Id": "other4",
    "Title": "Vacuum Pump"
  },
  {
    "Id": "other5",
    "Title": "Vacuum Pipe"
  },
  {
    "Id": "other6",
    "Title": "Vacuum Pipe Corner"
  },
  {
    "Id": "other7",
    "Title": "Gas Container"
  },
  {
    "Id": "other8",
    "Title": "Battery Container"
  },
  {
    "Id": "other9",
    "Title": "Gasoline"
  },
  {
    "Id": "other10",
    "Title": "Battery"
  },
  {
    "Id": "other11",
    "Title": "Potted Plant"
  },
  {
    "Id": "other12",
    "Title": "Small Potted Plant"
  },
  {
    "Id": "other13",
    "Title": "Potted Vine Plant"
  },
  {
    "Id": "other14",
    "Title": "Big Pot"
  },
  {
    "Id": "other15",
    "Title": "Potted Seed Plant"
  },
  {
    "Id": "other16",
    "Title": "Potted Blooming Cactus"
  },
  {
    "Id": "other17",
    "Title": "Potted Cactus"
  },
  {
    "Id": "other18",
    "Title": "Potted Blue Flower"
  },
  {
    "Id": "other19",
    "Title": "Spud Gun"
  },
  {
    "Id": "other20",
    "Title": "Spud Shotgun"
  },
  {
    "Id": "other21",
    "Title": "Spudling Gun"
  },
  {
    "Id": "other22",
    "Title": "Connect Tool"
  }
]