[
  {
    "Id": "other1",
    "Title": "Verbindungswerkzeug"
  },
  {
    "Id": "other2",
    "Title": "Zeichenwerkzeug"
  },
  {
    "Id": "other3",
    "Title": "Schweißwerkzeug"
  },
  {
    "Id": "other4",
    "Title": "Vacuum Pump"
  },
  {
    "Id": "other5",
    "Title": "Vacuum Pipe"
  },
  {
    "Id": "other6",
    "Title": "Vacuum Pipe Corner"
  },
  {
    "Id": "other7",
    "Title": "Topfpflanze"
  },
  {
    "Id": "other8",
    "Title": "Kleine Topfpflanze"
  },
  {
    "Id": "other9",
    "Title": "Rankenpflanze im Topf"
  },
  {
    "Id": "other10",
    "Title": "Großer Topf"
  },
  {
    "Id": "other11",
    "Title": "Setzling im Topf"
  },
  {
    "Id": "other12",
    "Title": "Blühender Kaktus im Topf"
  },
  {
    "Id": "other13",
    "Title": "Topfkaktus"
  },
  {
    "Id": "other14",
    "Title": "Blaue Blume im Topf"
  },
  {
    "Id": "other15",
    "Title": "Spud Gun"
  },
  {
    "Id": "other16",
    "Title": "Spud Shotgun"
  },
  {
    "Id": "other17",
    "Title": "Spudling Gun"
  },
  {
    "Id": "other18",
    "Title": "Verbindungswerkzeug"
  }
]